picohsm/APDU.py
picohsm/Algorithm.py
picohsm/DO.py
picohsm/ICCD.py
picohsm/PicoHSM.py
picohsm/RescuePicoKey.py
picohsm/SWCodes.py
picohsm/__init__.py
picohsm/_version.py
picohsm/const.py
picohsm/oid.py
picohsm/utils.py
picohsm/tools/__init__.py
pypicohsm-1.7.dist-info/METADATA
pypicohsm-1.7.dist-info/WHEEL
pypicohsm-1.7.dist-info/top_level.txt
pypicohsm-1.7.dist-info/RECORD
